ttmsd/__init__.py
ttmsd/admin.py
ttmsd/api.py
ttmsd/core.py
ttmsd/model.py
ttmsd/utils.py
ttmsd/htdocs/ttmsd.css
ttmsd/htdocs/ttmsd.js
ttmsd/templates/discord_payload.html
ttmsd/templates/msteams_dispatcher_admin.html
ttmsd/templates/msteams_dispatcher_payload_admin.html
ttmsd/templates/teams_payload.html
TracTicketMSTeamsDispatcher-0.7.0.dev0.dist-info/0BSD.txt
TracTicketMSTeamsDispatcher-0.7.0.dev0.dist-info/LGPL-2.1-or-later.txt
TracTicketMSTeamsDispatcher-0.7.0.dev0.dist-info/LicenseRef-Trac.txt
TracTicketMSTeamsDispatcher-0.7.0.dev0.dist-info/METADATA
TracTicketMSTeamsDispatcher-0.7.0.dev0.dist-info/MIT.txt
TracTicketMSTeamsDispatcher-0.7.0.dev0.dist-info/WHEEL
TracTicketMSTeamsDispatcher-0.7.0.dev0.dist-info/entry_points.txt
TracTicketMSTeamsDispatcher-0.7.0.dev0.dist-info/top_level.txt
TracTicketMSTeamsDispatcher-0.7.0.dev0.dist-info/RECORD
