Metadata-Version: 2.1
Name: TracTicketMSTeamsDispatcher
Version: 0.7.0.dev0
Summary: Send a message on ticket creation or update to a MS Teams channel
Home-page: https://github.com/rosjat/TracTicketMSTeamsDispatcherPlugin
Author: Markus Rosjat
License: LGPL-2.1
Keywords: trac
Classifier: Environment :: Plugins
Classifier: Environment :: Web Environment
Classifier: Framework :: Trac
Classifier: Intended Audience :: End Users/Desktop
Classifier: License :: OSI Approved :: GNU Lesser General Public License v2 (LGPLv2)
Classifier: License :: OSI Approved :: GNU Lesser General Public License v2 or later (LGPLv2+)
Classifier: Programming Language :: Python
Classifier: Programming Language :: Python :: 3.10
License-File: LICENSES/0BSD.txt
License-File: LICENSES/LGPL-2.1-or-later.txt
License-File: LICENSES/LicenseRef-Trac.txt
License-File: LICENSES/MIT.txt
Requires-Dist: requests
Requires-Dist: Trac (>=1.5)
Provides-Extra: dev
Requires-Dist: isort ; extra == 'dev'
Requires-Dist: black ; extra == 'dev'
Requires-Dist: mypy ; extra == 'dev'
Requires-Dist: pre-commit ; extra == 'dev'
Requires-Dist: pytest ; extra == 'dev'
Requires-Dist: pytest-mypy ; extra == 'dev'
Requires-Dist: setuptools (>=42) ; extra == 'dev'
Requires-Dist: setuptools-scm[toml] (>=3.4) ; extra == 'dev'
Requires-Dist: wheel ; extra == 'dev'
